odoo9_addon_crm_claim_operating_unit-9.0.1.0.0-py2.7-nspkg.pth
odoo9_addon_crm_claim_operating_unit-9.0.1.0.0.dist-info/DESCRIPTION.rst
odoo9_addon_crm_claim_operating_unit-9.0.1.0.0.dist-info/METADATA
odoo9_addon_crm_claim_operating_unit-9.0.1.0.0.dist-info/RECORD
odoo9_addon_crm_claim_operating_unit-9.0.1.0.0.dist-info/WHEEL
odoo9_addon_crm_claim_operating_unit-9.0.1.0.0.dist-info/metadata.json
odoo9_addon_crm_claim_operating_unit-9.0.1.0.0.dist-info/namespace_packages.txt
odoo9_addon_crm_claim_operating_unit-9.0.1.0.0.dist-info/top_level.txt
odoo_addons/crm_claim_operating_unit/README.rst
odoo_addons/crm_claim_operating_unit/__init__.py
odoo_addons/crm_claim_operating_unit/__openerp__.py
odoo_addons/crm_claim_operating_unit/models/__init__.py
odoo_addons/crm_claim_operating_unit/models/crm_claim.py
odoo_addons/crm_claim_operating_unit/models/crm_team.py
odoo_addons/crm_claim_operating_unit/security/crm_security.xml
odoo_addons/crm_claim_operating_unit/static/description/icon.png
odoo_addons/crm_claim_operating_unit/tests/__init__.py
odoo_addons/crm_claim_operating_unit/tests/test_crm_claim_operating_unit.py
odoo_addons/crm_claim_operating_unit/views/crm_claim_view.xml
