Metadata-Version: 2.0
Name: odoo9-addon-crm-claim-operating-unit
Version: 9.0.1.0.0
Summary: Operating Unit in CRM Claims
Home-page: http://www.eficent.com
Author: Eficent, Serpent Consulting Services Pvt. Ltd.,Odoo Community Association (OCA)
Author-email: support@odoo-community.org
License: LGPL-3
Platform: UNKNOWN
Classifier: Programming Language :: Python :: 2.7
Classifier: Framework :: Odoo
Classifier: License :: OSI Approved :: GNU Lesser General Public License v3 (LGPLv3)
Requires-Dist: odoo (<9.1a,>=9.0a)
Requires-Dist: odoo9-addon-operating-unit
Requires-Dist: odoo9-addon-sales-team-operating-unit
